[
    {
        "id": 37293,
        "title": "NASA finalizes science plans for Artemis 2 lunar flyby",
        "authors": [
            {
                "name": "Jeff Foust",
                "socials": {
                    "x": "https://x.com/jeff_foust",
                    "youtube": "",
                    "instagram": "",
                    "linkedin": "https://www.linkedin.com/in/jefffoust",
                    "mastodon": "https://mastodon.social/@jfoust",
                    "bluesky": "https://bsky.app/profile/jfoust.bsky.social"
                }
            }
        ],
        "url": "https://spacenews.com/nasa-finalizes-science-plans-for-artemis-2-lunar-flyby/",
        "image_url": "https://i0.wp.com/spacenews.com/wp-content/uploads/2026/04/art002e004357-large.jpg?fit=1024%2C768&ssl=1",
        "news_site": "SpaceNews",
        "summary": "\nWASHINGTON \u2014 As Artemis 2 approaches the moon, a NASA science team is finalizing plans for the observations they want the astronauts to perform during their flyby. At an April 4 briefing, a representative of the mission\u2019s science team said they were working to complete a plan of observations by the astronauts on April 6, [\u2026]\nThe post NASA finalizes science plans for Artemis 2 lunar flyby appeared first on SpaceNews.",
        "published_at": "2026-04-05T03:29:58Z",
        "updated_at": "2026-04-05T03:30:28.471744Z",
        "featured": false,
        "launches": [],
        "events": [],
        "sentiment_score": 0.175,
        "sentiment_label": "Positive"
    },
    {
        "id": 37292,
        "title": "Artemis II is going so well that we're left to talk about frozen urine",
        "authors": [
            {
                "name": "Eric Berger",
                "socials": null
            }
        ],
        "url": "https://arstechnica.com/space/2026/04/artemis-ii-is-going-so-well-that-were-left-to-talk-about-frozen-urine/",
        "image_url": "https://cdn.arstechnica.net/wp-content/uploads/2026/04/art002e004357large.jpg",
        "news_site": "Arstechnica",
        "summary": "\"I think the fixation on the toilet is kind of human nature.\"",
        "published_at": "2026-04-05T00:12:45Z",
        "updated_at": "2026-04-05T00:20:08.806812Z",
        "featured": false,
        "launches": [],
        "events": [],
        "sentiment_score": 0.14166666666666666,
        "sentiment_label": "Positive"
    },
    {
        "id": 37291,
        "title": "Orion Spacecraft Races Toward Historic Lunar Flyby in Artemis II Mission",
        "authors": [
            {
                "name": "Chris Bergin and Martijn Luinstra",
                "socials": null
            }
        ],
        "url": "https://www.nasaspaceflight.com/2026/04/orion-toward-lunar-flyby-artemis-ii/",
        "image_url": "https://www.nasaspaceflight.com/wp-content/uploads/2026/04/NSF-2026-04-04-22-29-14-828.jpg",
        "news_site": "NASASpaceflight",
        "summary": "As NASA\u2019s Artemis II mission enters its critical mid-flight phase, the Orion spacecraft\u2014carrying the first\u2026\nThe post Orion Spacecraft Races Toward Historic Lunar Flyby in Artemis II Mission appeared first on NASASpaceFlight.com.",
        "published_at": "2026-04-04T21:57:48Z",
        "updated_at": "2026-04-04T22:00:27.633022Z",
        "featured": false,
        "launches": [],
        "events": [],
        "sentiment_score": 0.0625,
        "sentiment_label": "Neutral"
    },
    {
        "id": 37290,
        "title": "Atlas 5 launches Amazon Leo satellites",
        "authors": [
            {
                "name": "Jeff Foust",
                "socials": {
                    "x": "https://x.com/jeff_foust",
                    "youtube": "",
                    "instagram": "",
                    "linkedin": "https://www.linkedin.com/in/jefffoust",
                    "mastodon": "https://mastodon.social/@jfoust",
                    "bluesky": "https://bsky.app/profile/jfoust.bsky.social"
                }
            }
        ],
        "url": "https://spacenews.com/atlas-5-launches-amazon-leo-satellites/",
        "image_url": "https://i0.wp.com/spacenews.com/wp-content/uploads/2026/04/55186765921_b24845973c_k.jpg?fit=1024%2C683&ssl=1",
        "news_site": "SpaceNews",
        "summary": "\nAn Atlas 5 launched the latest set of satellites for Amazon\u2019s broadband constellation April 4 as the company seeks to accelerate deployment of its spacecraft.\nThe post Atlas 5 launches Amazon Leo satellites appeared first on SpaceNews.",
        "published_at": "2026-04-04T20:27:36Z",
        "updated_at": "2026-04-04T20:30:29.683790Z",
        "featured": false,
        "launches": [],
        "events": [],
        "sentiment_score": 0.375,
        "sentiment_label": "Positive"
    },
    {
        "id": 37289,
        "title": "NASA Answers Your Most Pressing Artemis II Questions",
        "authors": [
            {
                "name": "NASA",
                "socials": null
            }
        ],
        "url": "https://www.nasa.gov/missions/nasa-answers-your-most-pressing-artemis-ii-questions/",
        "image_url": "https://images-assets.nasa.gov/image/art002e008487/art002e008487~large.jpg",
        "news_site": "NASA",
        "summary": "The first crewed test flight under NASA\u2019s Artemis program is underway. Four Artemis II astronauts are flying aboard NASA\u2019s Orion spacecraft around the Moon and back, as they test how the spacecraft\u2019s systems operate in a deep space environment. NASA astronauts Reid Wiseman, Victor Glover, and Christina Koch, and CSA (Canadian Space Agency) astronaut Jeremy [\u2026]",
        "published_at": "2026-04-04T19:44:31Z",
        "updated_at": "2026-04-04T19:50:22.099187Z",
        "featured": false,
        "launches": [],
        "events": [],
        "sentiment_score": 0.1875,
        "sentiment_label": "Positive"
    },
    {
        "id": 37288,
        "title": "Space Force budget would more than double in Trump\u2019s $1.5 trillion defense plan",
        "authors": [
            {
                "name": "Sandra Erwin",
                "socials": null
            }
        ],
        "url": "https://spacenews.com/space-force-budget-would-more-than-double-in-trumps-1-5-trillion-defense-plan/",
        "image_url": "https://i0.wp.com/spacenews.com/wp-content/uploads/2026/04/55183031918_33e332e0c7_k.jpg?fit=1024%2C683&ssl=1",
        "news_site": "SpaceNews",
        "summary": "\n$71 billion request for the U.S. Space Force for fiscal year 2027 includes more than $60 billion for procurement, research and development\nThe post Space Force budget would more than double in Trump\u2019s $1.5 trillion defense plan appeared first on SpaceNews.",
        "published_at": "2026-04-04T16:30:36Z",
        "updated_at": "2026-04-04T16:40:30.564009Z",
        "featured": false,
        "launches": [],
        "events": [],
        "sentiment_score": 0.2916666666666667,
        "sentiment_label": "Positive"
    },
    {
        "id": 37287,
        "title": "Illuminated in Orion",
        "authors": [
            {
                "name": "NASA",
                "socials": null
            }
        ],
        "url": "https://www.nasa.gov/image-article/illuminated-in-orion/",
        "image_url": "https://www.nasa.gov/wp-content/uploads/2026/04/55187055368-7ab1e4c6a4-o.jpg",
        "news_site": "NASA",
        "summary": "NASA astronaut Christina Koch reads on a tablet in the dimly lit Orion crew capsule in this April 3, 2026, photo. To the right of the image\u2019s center, CSA (Canadian Space Agency) astronaut Jeremy Hansen is seen in profile peering out of one of Orion\u2019s windows. Lights are turned off to avoid glare on the [\u2026]",
        "published_at": "2026-04-04T15:07:46Z",
        "updated_at": "2026-04-04T15:10:11.820789Z",
        "featured": false,
        "launches": [],
        "events": [],
        "sentiment_score": 0.09523809523809523,
        "sentiment_label": "Neutral"
    }
]