[
    {
        "id": 38293,
        "title": "Axiom and Prada advance design of spacesuit",
        "authors": [
            {
                "name": "Jeff Foust",
                "socials": {
                    "x": "https://x.com/jeff_foust",
                    "youtube": "",
                    "instagram": "",
                    "linkedin": "https://www.linkedin.com/in/jefffoust",
                    "mastodon": "https://mastodon.social/@jfoust",
                    "bluesky": "https://bsky.app/profile/jfoust.bsky.social"
                }
            }
        ],
        "url": "https://spacenews.com/axiom-and-prada-advance-design-of-spacesuit/",
        "image_url": "https://i0.wp.com/spacenews.com/wp-content/uploads/2026/06/axiomsuits.jpeg?fit=1024%2C677&ssl=1",
        "news_site": "SpaceNews",
        "summary": "\nAxiom Space unveiled the design of another element of the lunar spacesuit it is developing for NASA in partnership with luxury designer Prada.\nThe post Axiom and Prada advance design of spacesuit appeared first on SpaceNews.",
        "published_at": "2026-06-08T11:23:20Z",
        "updated_at": "2026-06-08T11:30:20.198802Z",
        "featured": false,
        "launches": [],
        "events": [],
        "sentiment_score": 0.25,
        "sentiment_label": "Positive"
    },
    {
        "id": 38292,
        "title": "Speed as a Strategic Advantage in Border Monitoring",
        "authors": [
            {
                "name": "BlackSky",
                "socials": null
            }
        ],
        "url": "https://spacenews.com/speed-as-a-strategic-advantage-in-border-monitoring/",
        "image_url": "https://i0.wp.com/spacenews.com/wp-content/uploads/2026/06/SpaceNews_BlackSky_Poland-Russiaborder_03April2026_167vehicles.jpg?fit=879%2C497&ssl=1",
        "news_site": "SpaceNews",
        "summary": "\nAcross Europe, border environments are becoming increasingly dynamic and complex. Activity can shift within hours\u2014vehicles reposition, staging areas disperse, small watercraft alter routes, and nodes of activity appear and disappear [\u2026]\nThe post Speed as a Strategic Advantage in Border Monitoring appeared first on SpaceNews.",
        "published_at": "2026-06-08T11:00:00Z",
        "updated_at": "2026-06-08T11:00:34.301657Z",
        "featured": false,
        "launches": [],
        "events": [],
        "sentiment_score": 0.030000000000000006,
        "sentiment_label": "Neutral"
    },
    {
        "id": 38291,
        "title": "ESA at ILA Berlin International Airshow 2026",
        "authors": [
            {
                "name": "ESA",
                "socials": null
            }
        ],
        "url": "https://www.esa.int/About_Us/Corporate_news/ESA_at_ILA_Berlin_International_Airshow_2026",
        "image_url": "https://www.esa.int/var/esa/storage/images/esa_multimedia/images/2026/06/europe_in_space_ila_2026/27312131-1-eng-GB/Europe_in_space_ILA_2026_card_full.jpg",
        "news_site": "ESA",
        "summary": "Under the theme 'Space4Future', the European Space Agency (ESA) will welcome visitors to the Space Pavilion at ILA Berlin International Airshow, Hall B, from\u00a010 to 14\u202fJune. From Moon exploration to climate monitoring, from navigation and telecommunication to European launchers, visitors to the pavilion will discover how space is shaping our future.",
        "published_at": "2026-06-08T08:18:00Z",
        "updated_at": "2026-06-08T08:50:13.233005Z",
        "featured": false,
        "launches": [],
        "events": [],
        "sentiment_score": 0.13333333333333333,
        "sentiment_label": "Positive"
    },
    {
        "id": 38290,
        "title": "ESA and EBRD to advance Earth observation for development and impact finance",
        "authors": [
            {
                "name": "ESA",
                "socials": null
            }
        ],
        "url": "https://www.esa.int/Applications/Observing_the_Earth/ESA_and_EBRD_to_advance_Earth_observation_for_development_and_impact_finance",
        "image_url": "https://www.esa.int/var/esa/storage/images/esa_multimedia/images/2026/06/esa_and_ebrd_sign_letter_of_intent_in_riga/27311442-1-eng-GB/ESA_and_EBRD_sign_letter_of_intent_in_Riga_card_full.jpg",
        "news_site": "ESA",
        "summary": "The European Space Agency (ESA) signed an agreement with the European Bank for Reconstruction and Development (EBRD), hailing a new era of cooperation with the aim of advancing the use of Earth observation data and services for development and impact finance initiatives.",
        "published_at": "2026-06-08T07:15:00Z",
        "updated_at": "2026-06-08T08:00:24.762976Z",
        "featured": false,
        "launches": [],
        "events": [],
        "sentiment_score": 0.04545454545454545,
        "sentiment_label": "Neutral"
    },
    {
        "id": 38289,
        "title": "UK startup NewOrbit raises $18.5 million in Series A round",
        "authors": [
            {
                "name": "Debra Werner",
                "socials": null
            }
        ],
        "url": "https://spacenews.com/uk-startup-neworbit-raises-18-5-million-in-series-a-round/",
        "image_url": "https://i0.wp.com/spacenews.com/wp-content/uploads/2026/06/rsz_neo_fromabove.jpg?fit=879%2C494&ssl=1",
        "news_site": "SpaceNews",
        "summary": "\nSAN FRANCISCO \u2013 NewOrbit Space, a UK startup developing satellites for very low Earth orbit (VLEO), has raised $18.5 million in a Series A investment round. With the funding, announced [\u2026]\nThe post UK startup NewOrbit raises $18.5 million in Series A round appeared first on SpaceNews.",
        "published_at": "2026-06-08T07:00:00Z",
        "updated_at": "2026-06-08T07:00:43.631990Z",
        "featured": false,
        "launches": [],
        "events": [],
        "sentiment_score": -0.07000000000000002,
        "sentiment_label": "Neutral"
    },
    {
        "id": 38288,
        "title": "OQ Technology plans direct-to-smartphone demo with cellular spectrum",
        "authors": [
            {
                "name": "Jason Rainbow",
                "socials": {
                    "x": "",
                    "youtube": "",
                    "instagram": "",
                    "linkedin": "https://www.linkedin.com/in/jasonrainbow",
                    "mastodon": "",
                    "bluesky": ""
                }
            }
        ],
        "url": "https://spacenews.com/oq-technology-plans-direct-to-smartphone-demo-with-cellular-spectrum/",
        "image_url": "https://i0.wp.com/spacenews.com/wp-content/uploads/2026/06/PR_OQ_Telefonica_logos.png?fit=1024%2C692&ssl=1",
        "news_site": "SpaceNews",
        "summary": "\nLuxembourg\u2019s OQ Technology plans to test direct-to-smartphone satellite connectivity next year in Germany using a local telco\u2019s cellular spectrum, setting up a challenge to U.S.-led services in the emerging market.\nThe post OQ Technology plans direct-to-smartphone demo with cellular spectrum appeared first on SpaceNews.",
        "published_at": "2026-06-08T06:30:00Z",
        "updated_at": "2026-06-08T06:40:20.889394Z",
        "featured": false,
        "launches": [],
        "events": [],
        "sentiment_score": 0.08333333333333333,
        "sentiment_label": "Neutral"
    },
    {
        "id": 38287,
        "title": "French Space Electronics Firm EREMS Completes \u20ac10 Million Expansion",
        "authors": [
            {
                "name": "European Spaceflight",
                "socials": null
            }
        ],
        "url": "https://europeanspaceflight.com/french-space-electronics-firm-erems-completes-e10-million-expansion/",
        "image_url": "https://europeanspaceflight.com/wp-content/uploads/2026/06/French-Space-Electronics-Firm-EREMS-Completes-E10-Million-Expansion.webp",
        "news_site": "European Spaceflight",
        "summary": "EREMS announced on 5 June the inauguration of its revamped Flourens facility in southwestern France following a three-year, \u20ac10 million expansion. Founded in 1979, EREMS specialises in the design and manufacture of electronic equipment used primarily for space applications. Most recently, the company has supplied key elements for Airbus Defence and Space\u2019s CO3D and Pl\u00e9iades [\u2026]\nThe post French Space Electronics Firm EREMS Completes \u20ac10 Million Expansion appeared first on European Spaceflight.",
        "published_at": "2026-06-08T06:10:05Z",
        "updated_at": "2026-06-08T06:10:11.572521Z",
        "featured": false,
        "launches": [],
        "events": [],
        "sentiment_score": 0.06818181818181818,
        "sentiment_label": "Neutral"
    },
    {
        "id": 38286,
        "title": "NASA concludes MAVEN mission at Mars, uses data to discover new atmospheric phenomenon",
        "authors": [
            {
                "name": "Haygen Warren",
                "socials": null
            }
        ],
        "url": "https://www.nasaspaceflight.com/2026/06/maven-end-of-mission/",
        "image_url": "https://www.nasaspaceflight.com/wp-content/uploads/2026/06/maven_mars_sunrise.png",
        "news_site": "NASASpaceflight",
        "summary": "Following a six-month battle to regain communication with its Mars Atmosphere and Volatile Evolution (MAVEN)\u2026\r\nThe post NASA concludes MAVEN mission at Mars, uses data to discover new atmospheric phenomenon appeared first on NASASpaceFlight.com.",
        "published_at": "2026-06-07T20:11:48Z",
        "updated_at": "2026-06-08T06:38:10.724944Z",
        "featured": false,
        "launches": [
            {
                "launch_id": "404bc5c5-79b8-4c7e-9919-a18ca202e38c",
                "provider": "Launch Library 2"
            }
        ],
        "events": [
            {
                "event_id": 1489,
                "provider": "Launch Library 2"
            }
        ],
        "sentiment_score": 0.08712121212121211,
        "sentiment_label": "Neutral"
    },
    {
        "id": 38285,
        "title": "What\u2019s Happening in Space Policy June 7-13, 2026",
        "authors": [
            {
                "name": "Marcia Smith",
                "socials": null
            }
        ],
        "url": "https://spacepolicyonline.com/news/whats-happening-in-space-policy-june-7-13-2026/",
        "image_url": "https://spacepolicyonline.com/wp-content/uploads/2026/02/Artemis-II-in-walkway-300x200.jpg",
        "news_site": "SpacePolicyOnline.com",
        "summary": "Here is SpacePolicyOnline.com\u2019s list of space policy events for the week of June 7-13, 2026 and any insight we can offer about them.\u00a0 The House and Senate are in session [\u2026]",
        "published_at": "2026-06-07T19:48:26Z",
        "updated_at": "2026-06-07T19:50:22.987104Z",
        "featured": false,
        "launches": [],
        "events": [],
        "sentiment_score": 0.0,
        "sentiment_label": "Neutral"
    },
    {
        "id": 38284,
        "title": "Live coverage: SpaceX to launch Falcon 9 rocket booster on record-breaking 35th flight",
        "authors": [
            {
                "name": "Will Robinson-Smith",
                "socials": null
            }
        ],
        "url": "https://spaceflightnow.com/2026/06/07/live-coverage-spacex-to-launch-falcon-9-rocket-booster-on-record-breaking-35th-flight/",
        "image_url": "http://spaceflightnow.com/wp-content/uploads/2025/12/20250827_Starlink_10_11_30.jpg",
        "news_site": "Spaceflight Now",
        "summary": "The Starlink 10-35 mission will be the 53rd dedicated launch for the satellite constellation. Liftoff from pad 40 at Cape Canaveral Space Force Station is scheduled during a window that opens at 6:07 a.m. EDT (1007 UTC).",
        "published_at": "2026-06-07T19:08:47Z",
        "updated_at": "2026-06-08T06:38:25.032709Z",
        "featured": false,
        "launches": [
            {
                "launch_id": "114577dc-7617-461c-aaeb-9bd0f64b5a4b",
                "provider": "Launch Library 2"
            }
        ],
        "events": [],
        "sentiment_score": 0.13636363636363635,
        "sentiment_label": "Positive"
    }
]